uboxcars_py-15.0.0.dist-info/METADATA
uboxcars_py-15.0.0.dist-info/WHEEL
uboxcars_py/__init__.py
uboxcars_py/__init__.pyi
uboxcars_py/py.typed
uboxcars_py/uboxcars_py.pyd
uboxcars_py-15.0.0.dist-info/RECORD
