Metadata-Version: 2.4
Name: uboxcars_py
Version: 15.0.0
Author: Justus K <justus.k@protonmail.com>, Matthew Mage <sciguymjm@gmail.com>
Author-email: Justus K <justus.k@protonmail.com>, Matthew Mage <sciguymjm@gmail.com>
